audioace/__init__.py
audioace-0.0.4.dist-info/LICENSE
audioace-0.0.4.dist-info/METADATA
audioace-0.0.4.dist-info/WHEEL
audioace-0.0.4.dist-info/top_level.txt
audioace-0.0.4.dist-info/RECORD
