Metadata-Version: 2.1
Name: audioace
Version: 0.0.4
Summary: Downloads your favourite music
Home-page: https://github.com/VikranthMaster/AudioAce.git
Author: Vikranth
Author-email: <vikrantht32@gmail.com>
Project-URL: Bug Tracker, https://github.com/VikranthMaster/AudioAce/issues
Classifier: Programming Language :: Python :: 3
Classifier: Operating System :: Microsoft :: Windows
License-File: LICENSE
Requires-Dist: pytube
Requires-Dist: pywhatkit
Requires-Dist: requests
Requires-Dist: moviepy
Requires-Dist: spotipy
